pnlp/__init__.py
pnlp/pcut.py
pnlp/penh.py
pnlp/piop.py
pnlp/pmag.py
pnlp/pnorm.py
pnlp/ptrans.py
pnlp/ptxt.py
pnlp/utils.py
pnlp/stopwords/ReadMe.md
pnlp/stopwords/__init__.py
pnlp/stopwords/chinese_stopwords.txt
pnlp/stopwords/english_stopwords.txt
pnlp-0.4.16.dist-info/LICENSE
pnlp-0.4.16.dist-info/METADATA
pnlp-0.4.16.dist-info/WHEEL
pnlp-0.4.16.dist-info/top_level.txt
pnlp-0.4.16.dist-info/RECORD
