Metadata-Version: 2.1
Name: pnlp
Version: 0.4.16
Summary: A pre/post-processing tool for NLP.
Home-page: https://github.com/hscspring/pnlp
Author: Yam
Author-email: haoshaochun@gmail.com
Classifier: Programming Language :: Python :: 3
Classifier: License :: OSI Approved :: Apache Software License
Classifier: Operating System :: OS Independent
License-File: LICENSE
Requires-Dist: addict
Requires-Dist: pyyaml
Requires-Dist: dill
Requires-Dist: numpy
